zorg_seeed/motor_shield.py
zorg_seeed/__init__.py
tests/__init__.py
tests/smoke_tests/test_commands.py
tests/smoke_tests/__init__.py
zorg_seeed-0.0.1.dist-info/RECORD
zorg_seeed-0.0.1.dist-info/top_level.txt
zorg_seeed-0.0.1.dist-info/metadata.json
zorg_seeed-0.0.1.dist-info/zip-safe
zorg_seeed-0.0.1.dist-info/METADATA
zorg_seeed-0.0.1.dist-info/DESCRIPTION.rst
zorg_seeed-0.0.1.dist-info/WHEEL
